indiek/gui/__init__.py
indiek/gui/app.py
indiek/gui/items.py
indiek/gui/styles.py
indiek_gui-0.0.4.dist-info/LICENSE
indiek_gui-0.0.4.dist-info/METADATA
indiek_gui-0.0.4.dist-info/WHEEL
indiek_gui-0.0.4.dist-info/entry_points.txt
indiek_gui-0.0.4.dist-info/top_level.txt
indiek_gui-0.0.4.dist-info/RECORD
