Metadata-Version: 2.1
Name: indiek-gui
Version: 0.0.4
Summary: Tkinter GUI for IndieK
Home-page: https://pypi.org/project/indiek-gui/
Author: Adrian Ernesto Radillo
Author-email: adrian.radillo@gmail.com
License: GNU Affero General Public License v3.0
Project-URL: GitHub, https://github.com/indiek/indiek-gui
Project-URL: Documentation, https://indiekgui.readthedocs.io/en/latest/
Requires-Python: >=3.8
License-File: LICENSE
Requires-Dist: indiek-core (==0.1.4)
Provides-Extra: dev
Requires-Dist: pytest ; extra == 'dev'
Requires-Dist: pytest-pep8 ; extra == 'dev'
Requires-Dist: pytest-cov ; extra == 'dev'
